openfieldreaderwrapper/__init__.py
openfieldreaderwrapper/openfieldreaderwrapper.py
openfieldreaderwrapper-1.0.1.dist-info/METADATA
openfieldreaderwrapper-1.0.1.dist-info/WHEEL
openfieldreaderwrapper-1.0.1.dist-info/top_level.txt
openfieldreaderwrapper-1.0.1.dist-info/RECORD
