Metadata-Version: 2.1
Name: openfieldreaderwrapper
Version: 1.0.1
Summary: A wrapper around the openfieldreader command line tool to automatically detect paper-based form fields.
Home-page: https://github.com/OpenFieldReader/OpenFieldReaderWrapper
Author: Philip Doxakis
Author-email: philip@doxakis.com
License: MIT
Keywords: icr
Platform: UNKNOWN
Classifier: Development Status :: 4 - Beta
Classifier: Intended Audience :: Developers
Classifier: License :: OSI Approved :: MIT License
Classifier: Programming Language :: Python :: 2
Classifier: Programming Language :: Python :: 2.7
Classifier: Programming Language :: Python :: 3
Classifier: Programming Language :: Python :: 3.3
Classifier: Programming Language :: Python :: 3.4
Classifier: Programming Language :: Python :: 3.5
Classifier: Programming Language :: Python :: 3.6
Requires-Dist: opencv-python
